xctpol/__init__.py
xctpol/backup_ste.py
xctpol/ste.py
xctpol/utils.py
xctpol/xctpol.py
xctpol-1.0.1.dist-info/METADATA
xctpol-1.0.1.dist-info/WHEEL
xctpol-1.0.1.dist-info/top_level.txt
xctpol-1.0.1.dist-info/RECORD
