Metadata-Version: 2.2
Name: xctpol
Version: 1.0.1
Summary: Exciton-polaron calculations
Author: Krishnaa Vadivel
Author-email: krishnaa.vadivel@yale.edu
Requires: numpy
Requires: xctph
Requires: cython
Requires: fp_workflow
Dynamic: author
Dynamic: author-email
Dynamic: requires
Dynamic: summary
